sgmusic/__init__.py
sgmusic/py.typed
sgmusic-0.1.5.dist-info/WHEEL
sgmusic-0.1.5.dist-info/METADATA
sgmusic-0.1.5.dist-info/RECORD
