Metadata-Version: 2.1
Name: sgmusic
Version: 0.1.5
Summary: 
Home-page: https://github.com/SG60/sgmusic
Author: Sam Greening
Author-email: samjg60@gmail.com
Requires-Python: >=3.9,<4
Classifier: Programming Language :: Python :: 3
Classifier: Programming Language :: Python :: 3.10
Classifier: Programming Language :: Python :: 3.9
Requires-Dist: sympy (>=1.10,<2.0)
Project-URL: Repository, https://github.com/SG60/sgmusic
